random_number_mcp/__init__.py
random_number_mcp/server.py
random_number_mcp/tools.py
random_number_mcp/utils.py
random_number_mcp-0.1.1.dist-info/METADATA
random_number_mcp-0.1.1.dist-info/WHEEL
random_number_mcp-0.1.1.dist-info/entry_points.txt
random_number_mcp-0.1.1.dist-info/licenses/LICENSE
random_number_mcp-0.1.1.dist-info/RECORD
