Metadata-Version: 2.4
Name: random-number-mcp
Version: 0.1.1
Summary: Random-number utilities exposed via Model Context Protocol
Project-URL: Homepage, https://github.com/zazencodes/random-number-mcp
Project-URL: Repository, https://github.com/zazencodes/random-number-mcp
Project-URL: Issues, https://github.com/zazencodes/random-number-mcp/issues
Author-email: Alexander Galea <alex@galea.dev>
License: MIT
License-File: LICENSE
Keywords: cryptographic,generator,mcp,model-context-protocol,number,pseudorandom,random,rng,utility
Classifier: Development Status :: 4 - Beta
Classifier: Intended Audience :: Developers
Classifier: License :: OSI Approved :: MIT License
Classifier: Programming Language :: Python :: 3.10
Classifier: Programming Language :: Python :: 3.11
Classifier: Programming Language :: Python :: 3.12
Classifier: Topic :: Software Development :: Libraries :: Python Modules
Requires-Python: >=3.10
Requires-Dist: fastmcp<3.0,>=2.0
Provides-Extra: dev
Requires-Dist: mypy>=1.0; extra == 'dev'
Requires-Dist: pytest-cov>=4.0; extra == 'dev'
Requires-Dist: pytest>=7.0; extra == 'dev'
Requires-Dist: ruff>=0.1.0; extra == 'dev'
